srtmerge-1.0.dist-info/DESCRIPTION.rst
srtmerge-1.0.dist-info/pydist.json
srtmerge-1.0.dist-info/RECORD
srtmerge-1.0.dist-info/METADATA
srtmerge-1.0.dist-info/top_level.txt
srtmerge-1.0.dist-info/WHEEL
srtmerge-1.0.dist-info/entry_points.txt
srtmerge/__init__.py
srtmerge/srt.py
srtmerge/cli.py
srtmerge-1.0.data/scripts/srtmerge
